gender_bender/__init__.py
gender_bender/gender_tools.py
gender_bender/language_models/README.md
gender_bender/language_models/english/female_names
gender_bender/language_models/english/male_names
gender_bender/language_models/english/words
gender_bender/pluralize.py
gender_bender-0.1.3.dist-info/LICENSE
gender_bender-0.1.3.dist-info/WHEEL
gender_bender-0.1.3.dist-info/METADATA
gender_bender-0.1.3.dist-info/RECORD
