Metadata-Version: 2.1
Name: gender-bender
Version: 0.1.3
Summary: Flips the gender in a text snippet or epub
Home-page: https://github.com/Garrett-R/gender_bender
License: Apache-2.0
Author: Garrett-R
Requires-Python: >=3.6,<4.0
Classifier: License :: OSI Approved :: Apache Software License
Classifier: Programming Language :: Python :: 3
Classifier: Programming Language :: Python :: 3.6
Classifier: Programming Language :: Python :: 3.7
Classifier: Programming Language :: Python :: 3.8
Requires-Dist: EbookLib (>=0.17.1,<0.18.0)
Requires-Dist: gender-guesser (>=0.4.0,<0.5.0)
Requires-Dist: spacy (>=2.3.2,<3.0.0)
Requires-Dist: termcolor (>=1.1.0,<2.0.0)
Requires-Dist: titlecase (>=1.1.1,<2.0.0)
Project-URL: Repository, https://github.com/Garrett-R/gender_bender
